{
    "配置文件版本": "V3",
    "用户名": "默认配置",
    "调试模式": 1,
    "控制模式": 1,
    "串口": "",
    "截图模式": 4,
    "模拟器分辨率": 2,
    "窗口类名": [
        "Qt5156QWindowIcon",
        "LDPlayerMainFrame"
    ],
    "窗口标题": [
        "雷电模拟器",
        "MuMu模拟器12",
        "火影忍者"
    ],
    "MuMu安装路径": "",
    "MuMu实例索引": 1,
    "MuMu操作应用包名": "com.tencent.KiHan",
    "雷电安装路径": "",
    "雷电实例索引": 0,
    "扫描间隔": 1000,
    "二级密码": "",
    "键位": [
        [
            1543,
            835
        ],
        [
            1457,
            864
        ],
        [
            1467,
            774
        ],
        [
            1550,
            733
        ],
        [
            1395,
            787
        ],
        [
            1458,
            703
        ],
        [
            1292,
            862
        ],
        [
            1369,
            861
        ],
        [
            1538,
            645
        ],
        [
            273,
            691
        ]
    ],
    "任务": {
    "登录奖励": {
        "是否启用": false,
        "下次执行时间": 0,
        "执行参数": {},
        "执行进度": {},
        "优先级": -6,
        "临时提权": false,
        "描述": "由于火影的登录奖励在游戏内过了5点需要退出重进才能领取，所以该任务默认会重启游戏\n如果你已经进入游戏领取了登录奖励，记得运行程序前关闭这个任务，并在下次运行时打开",
        "类型": 0
    },
    "高级忍者招募": {
        "是否启用": false,
        "下次执行时间": 0,
        "执行参数": {},
        "执行进度": {},
        "优先级": 0,
        "临时提权": false,
        "描述": "",
        "类型": 3
    },
    "排行榜点赞": {
        "是否启用": false,
        "下次执行时间": 0,
        "执行参数": {},
        "执行进度": {},
        "优先级": 0,
        "临时提权": false,
        "描述": "",
        "类型": 0
    },
    "每周胜场": {
        "是否启用": false,
        "下次执行时间": 0,
        "执行参数": {},
        "执行进度": {},
        "优先级": 14,
        "临时提权": false,
        "描述": "注意：该任务会直接使用当前匹配阵容，请提前设置好阵容防止掉胜率，需要配置键位",
        "类型": 1
    },
    "每月签到": {
        "是否启用": false,
        "下次执行时间": 0,
        "执行参数": {},
        "执行进度": {},
        "优先级": -2,
        "临时提权": false,
        "描述": "",
        "类型": 0
    },
    "购买体力": {
        "是否启用": false,
        "下次执行时间": 0,
        "执行参数": {
            "购买体力次数": {
                "描述": "设为0则不会购买体力",
                "类型": "INT",
                "最小值": 0,
                "最大值": 100,
                "当前值": 0
            }
        },
        "执行进度": {
            "已购买体力次数": 0
        },
        "优先级": -2,
        "临时提权": false,
        "描述": "需要配置二级密码",
        "类型": 0
    },
    "赛季胜场": {
        "是否启用": false,
        "下次执行时间": 0,
        "执行参数": {},
        "执行进度": {},
        "优先级": 15,
        "临时提权": false,
        "描述": "注意：该任务会直接使用当前匹配阵容，请提前设置好阵容防止掉胜率，需要配置键位",
        "类型": 2
    },
    "团本": {
        "是否启用": false,
        "下次执行时间": 0,
        "执行参数": {},
        "执行进度": {},
        "优先级": 16,
        "临时提权": false,
        "描述": "待开发",
        "类型": 1
    },
    "更多玩法": {
        "是否启用": false,
        "下次执行时间": 0,
        "执行参数": {},
        "执行进度": {},
        "优先级": 14,
        "临时提权": false,
        "描述": "自动刷满2100积分宝箱结束，需自己领取奖励，需要配置键位",
        "类型": 1
    },
    "金币招财": {
        "是否启用": false,
        "下次执行时间": 0,
        "执行参数": {
            "招财次数": {
                "描述": "该选项包含免费的次数，所以默认为2",
                "类型": "INT",
                "最小值": 0,
                "最大值": 100,
                "当前值": 0
            }
        },
        "执行进度": {
            "已招财次数": 0
        },
        "优先级": -2,
        "临时提权": false,
        "描述": "需要配置二级密码",
        "类型": 0
    },
    "小队突袭": {
        "是否启用": false,
        "下次执行时间": 0,
        "执行参数": {
            "四倍奖励次数": {
                "描述": "设置为0则不会勾选四倍奖励",
                "类型": "INT",
                "最小值": 0,
                "最大值": 2,
                "当前值": 0
            }
        },
        "执行进度": {
            "已领取四倍奖励次数": 0
        },
        "优先级": 0,
        "临时提权": false,
        "描述": "请确保已经使用自动通关一次，否则程序不会自动攻击，因为游戏内的自动通关更智能\n如果设置四倍奖励次数大于0，则需要配置二级密码\n请确保战力足够自动通关",
        "类型": 0
    },
    "组织祈福": {
        "是否启用": false,
        "下次执行时间": 0,
        "执行参数": {},
        "执行进度": {},
        "优先级": 0,
        "临时提权": false,
        "描述": "支持普通焚香祈福和超影祈福",
        "类型": 0
    },
    "好友体力": {
        "是否启用": false,
        "下次执行时间": 0,
        "执行参数": {},
        "执行进度": {},
        "优先级": -2,
        "临时提权": false,
        "描述": "自动赠送&领取",
        "类型": 0
    },
    "普通忍者招募": {
        "是否启用": false,
        "下次执行时间": 0,
        "执行参数": {},
        "执行进度": {},
        "优先级": 0,
        "临时提权": false,
        "描述": "",
        "类型": 0
    },
    "每日分享": {
        "是否启用": false,
        "下次执行时间": 0,
        "执行参数": {},
        "执行进度": {},
        "优先级": 0,
        "临时提权": false,
        "描述": "模拟器需要安装QQ/微信（取决于你的区）",
        "类型": 0
    },
    "丰饶之间": {
        "是否启用": false,
        "下次执行时间": 0,
        "执行参数": {},
        "执行进度": {},
        "优先级": 0,
        "临时提权": false,
        "描述": "需要配置键位",
        "类型": 0
    },
    "一乐外卖": {
        "是否启用": false,
        "下次执行时间": 0,
        "执行参数": {},
        "执行进度": {},
        "优先级": -2,
        "临时提权": false,
        "描述": "",
        "类型": 0
    },
    "任务集会所": {
        "是否启用": false,
        "下次执行时间": 0,
        "执行参数": {},
        "执行进度": {},
        "优先级": 0,
        "临时提权": false,
        "描述": "由于接取算法未实现，超影特权用户收益不能最大化",
        "类型": 0
    },
    "每日胜场": {
        "是否启用": false,
        "下次执行时间": 0,
        "执行参数": {},
        "执行进度": {},
        "优先级": 7,
        "临时提权": false,
        "描述": "注意：该任务会直接使用当前匹配阵容，请提前设置好阵容防止掉胜率，需要配置键位",
        "类型": 0
    },
    "忍法帖点赞分享": {
        "是否启用": false,
        "下次执行时间": 0,
        "执行参数": {},
        "执行进度": {},
        "优先级": 0,
        "临时提权": false,
        "描述": "模拟器需要安装QQ/微信（取决于你的区）",
        "类型": 1
    },
    "生存挑战": {
        "是否启用": false,
        "下次执行时间": 0,
        "执行参数": {},
        "执行进度": {},
        "优先级": 0,
        "临时提权": false,
        "描述": "请保证战力能扫荡过生存挑战，否则收益没有手打高",
        "类型": 0
    },
    "修行之路": {
        "是否启用": false,
        "下次执行时间": 0,
        "执行参数": {},
        "执行进度": {},
        "优先级": 0,
        "临时提权": false,
        "描述": "",
        "类型": 1
    },
    "秘境探险": {
        "是否启用": false,
        "下次执行时间": 0,
        "执行参数": {},
        "执行进度": {},
        "优先级": 7,
        "临时提权": false,
        "描述": "自动清空所有秘境挑战券，耗时可能较长；需要配置键位\n请确保战力足够连点通过落岩，烈炎，雷霆，水牢，罡体秘境，否则可能卡死\n忍者请选择须佐鼬，或其他远程灌伤忍者，自行尝试",
        "类型": 0
    },
    "情报站": {
        "是否启用": false,
        "下次执行时间": 0,
        "执行参数": {},
        "执行进度": {
            "浏览卷轴":false,
            "浏览村口":false,
            "浏览忍者站":false,
            "情报站签到":false,
            "浏览金币助手":false,
            "领取情报站活跃度":false,
            "40活跃度奖励已领取":false,
            "60活跃度奖励已领取":false,
            "100活跃度奖励已领取":false
        },
        "优先级": 9,
        "临时提权": false,
        "描述": "该任务可能因为网络连接差导致失败，请务必确保网络连接正常",
        "类型": 0
    },
    "冒险副本": {
        "是否启用": false,
        "下次执行时间": 0,
        "执行参数": {},
        "执行进度": {},
        "优先级": -1,
        "临时提权": false,
        "描述": "请保证自己在模拟器上手动扫荡过一次精英副本\n否则任务会勾选全选以达到通过任务的目的",
        "类型": 0
    },
    "消耗体力": {
        "是否启用": false,
        "下次执行时间": 0,
        "执行参数": {
            "体力消耗方式": {
                "描述": "选择哪种方式则会在完成日常之后优先使用该方式消耗体力\n举例：如果选择优先装备合成，则每天做完日常任务（包括冒险副本）之后\n会先调用装备合成，再调用冒险副本，消耗掉获得的体力，反之亦然",
                "类型": "COMBOX",
                "枚举列表": [
                    "装备合成",
                    "冒险副本"
                ],
                "当前值": 0
            },
            "合成目标装备": {
                "描述": "你想要合成的装备部位",
                "类型": "COMBOX",
                "枚举列表": [
                    "武器",
                    "头盔",
                    "胸甲",
                    "忍之书",
                    "项链",
                    "戒指"
                ],
                "当前值": 0
            }
        },
        "执行进度": {
            "任务1执行结束": false
        },
        "优先级": 10,
        "临时提权": false,
        "描述": "自动消耗体力，提供两种方式：\n[装备合成]：体力合成目标装备，支持自动扫荡，合成和装备\n[冒险副本]：自动按照勾选的扫荡，如果如果没有勾选则全选扫荡",
        "类型": 3
    },
    "活跃度奖励": {
        "是否启用": false,
        "下次执行时间": 0,
        "执行参数": {},
        "执行进度": {
            "10活跃度已领取": false,
            "40活跃度已领取": false,
            "80活跃度已领取": false,
            "100活跃度已领取": false,
            "周活跃礼已领取": false
        },
        "优先级": 11,
        "临时提权": false,
        "描述": "自动领取活跃度和周活跃大礼",
        "类型": 0
    },
    "清空邮件": {
        "是否启用": false,
        "下次执行时间": 0,
        "执行参数": {},
        "执行进度": {},
        "优先级": -2,
        "临时提权": false,
        "描述": "",
        "类型": 0
    },
    "本服要塞战": {
        "是否启用": false,
        "下次执行时间": 0,
        "执行参数": {
            "目标要塞": {
                "描述": "",
                "类型": "COMBOX",
                "枚举列表": [
                    "火之要塞",
                    "水之要塞",
                    "土之要塞",
                    "风之要塞",
                    "雷之要塞",
                    "汤之要塞",
                    "田之要塞",
                    "铁之要塞",
                    "熊之要塞",
                    "草之要塞",
                    "雨之要塞",
                    "海之要塞",
                    "川之要塞",
                    "泷之要塞",
                    "云之要塞",
                    "鸟之要塞",
                    "涡之要塞",
                    "霜之要塞"
                ],
                "当前值": 0
            }
        },
        "执行进度": {},
        "优先级": -5,
        "临时提权": false,
        "描述": "[测试]需要配置键位，默认自动挂在火要塞刷\n如果是低战请使用最弱的阵容和无攻击判定秘卷，不要拖慢刷的速度才能保证刷完",
        "类型": 1
    },
    "跨服要塞战": {
        "是否启用": false,
        "下次执行时间": 0,
        "执行参数": {},
        "执行进度": {},
        "优先级": -5,
        "临时提权": false,
        "描述": "待开发",
        "类型": 2
    },
    "叛忍来袭": {
        "是否启用": false,
        "下次执行时间": 0,
        "执行参数": {},
        "执行进度": {},
        "优先级": -4,
        "临时提权": false,
        "描述": "待开发",
        "类型": 1
    },
    "组织争霸": {
        "是否启用": false,
        "下次执行时间": 0,
        "执行参数": {},
        "执行进度": {},
        "优先级": -5,
        "临时提权": false,
        "描述": "待开发",
        "类型": 2
    },
    "巅峰对决": {
        "是否启用": false,
        "下次执行时间": 0,
        "执行参数": {},
        "执行进度": {},
        "优先级": -5,
        "临时提权": false,
        "描述": "待开发",
        "类型": 2
    },
    "追击晓组织": {
        "是否启用": false,
        "下次执行时间": 0,
        "执行参数": {},
        "执行进度": {},
        "优先级": 0,
        "临时提权": false,
        "描述": "自动领取追击晓组织奖励，不会自动扫荡和战斗",
        "类型": 1
    },
    "天地战场": {
        "是否启用": false,
        "下次执行时间": 0,
        "执行参数": {
            "选择战场": {
                "描述": "",
                "类型": "COMBOX",
                "枚举列表": [
                    "天之战场",
                    "地之战场"
                ],
                "当前值": 1
            }
        },
        "执行进度": {},
        "优先级": -5,
        "临时提权": false,
        "描述": "[测试]需要配置键位，自动上柱，能不能凑满1600取决于匹配的组织活不活跃",
        "类型": 1
    },
    "商城奖励": {
        "是否启用": false,
        "下次执行时间": 0,
        "执行参数": {},
        "执行进度": {},
        "优先级": 0,
        "临时提权": false,
        "描述": "领取15000铜币的蚊子腿",
        "类型": 0
    },
    "无差别预选赛": {
        "是否启用": false,
        "下次执行时间": 0,
        "执行参数": {
            "选择刷取方式": {
                "描述": "[7场]你一场都不用打，程序刷满参与7场，无法拿上榜奖励和获胜奖励\n[30场]你自己打赢6场，程序刷满参与30场，可拿上榜奖励",
                "类型": "COMBOX",
                "枚举列表": [
                    "7场",
                    "30场"
                ],
                "当前值": 0
            }
        },
        "执行进度": {},
        "优先级": 0,
        "临时提权": false,
        "描述": "[测试]自动刷取无差别预选赛场次，用完记得关",
        "类型": 4
    },
    "积分赛奖励": {
        "是否启用": false,
        "下次执行时间": 0,
        "执行参数": {},
        "执行进度": {},
        "优先级": 0,
        "临时提权": false,
        "描述": "自动领取每日积分赛奖励，不会进行战斗",
        "类型": 0
    }}
}